{
  "id": "ce-iot-predictive-maintenance-loop",
  "industry_lane": "consumer-electronics-iot",
  "scenario_family": "predictive-maintenance",
  "keywords": [
    "故障",
    "维护",
    "预测",
    "告警",
    "维修",
    "维保",
    "设备健康"
  ],
  "scenario": {
    "name": "设备健康驱动的预测性维护闭环",
    "target_users": "售后运营负责人、维修工程团队、设备运营团队",
    "business_problem": "故障识别滞后、维修和备件准备高度依赖经验，无法从被动报修转向主动维护。",
    "improvement_goal": "结合实时状态、历史维修和风险评分，提前识别高风险设备并推动主动维护动作。"
  },
  "opportunity": {
    "statement": "对消费电子 IoT 企业来说，预测性维护是最容易证明 AI 能直接降低服务成本并提升设备可用性的切口之一。",
    "why_now": "客户已经具备基础联网和售后数据，但还没有把遥测、告警、维修知识和处置动作串成统一闭环。",
    "supporting_points": [
      "高频维修和重复故障直接推高服务成本",
      "设备在线数据已经具备做风险预警和趋势判断的基础",
      "一旦跑通，可扩展到备件预测、主动保养和会员服务"
    ]
  },
  "current_process": [
    "设备出现故障后由用户报修或客服触发工单",
    "售后人员人工查看状态、历史维修记录和故障码",
    "经验型判断故障原因和维修优先级",
    "按经验安排备件、工程师和回访",
    "处理结果回写工单，但难以沉淀为统一预测能力"
  ],
  "pain_points": [
    "高风险设备无法提前识别，只能等用户报修",
    "维修优先级和备件准备依赖经验，效率不稳定",
    "历史维修经验和实时状态没有形成统一判断模型"
  ],
  "recommended_cards": {
    "business_scenario": [
      "设备维护"
    ],
    "input_perception": [
      "设备状态数据",
      "数据输入"
    ],
    "understanding_analysis": [
      "异常检测",
      "风险预测",
      "数据分析"
    ],
    "generation_interaction": [
      "文本生成",
      "自动回答"
    ],
    "execution_closure": [
      "流程优化",
      "自动履行",
      "人机交互"
    ]
  },
  "ai_flow": {
    "trigger": "系统识别到设备状态异常、告警频次上升或健康评分下降",
    "steps": [
      "系统持续接入遥测、告警、维修记录和使用行为数据",
      "AI 判断故障风险、预测维修窗口并给出优先级",
      "AI 生成维护建议、备件准备和客服沟通提示",
      "高风险设备自动触发保养提醒、工单或人工介入",
      "处理结果回写后继续优化预测模型和维护策略"
    ],
    "closure": "形成从设备健康识别、风险预测到主动维护动作的闭环",
    "narrative": "该场景适合展示消费电子 IoT 客户如何基于设备数据，把售后体系从被动响应升级为主动维护。"
  },
  "prototype": {
    "name": "预测性维护运营台",
    "goal": "为售后和设备运营团队提供统一的设备健康评分、风险预警和维护动作入口",
    "surface": "设备健康与维护运营台",
    "user_flow": [
      "查看设备健康评分和高风险设备列表",
      "读取 AI 给出的风险原因、维护建议和优先级",
      "一键触发保养提醒、工单流转或人工复核"
    ],
    "mock_scope": [
      "设备健康评分面板",
      "风险预警与原因解释区",
      "维护动作和工单联动区"
    ],
    "value_statement": "让售后团队从等故障发生再处理，转向基于健康评分和风险预测的主动维护运营。"
  },
  "product_mapping": [
    {
      "capability": "设备遥测与状态底座",
      "products": [
        "EMQX",
        "DataLayers"
      ],
      "delivery": "状态采集与时序数据底座"
    },
    {
      "capability": "故障预测与风险评分",
      "products": [
        "Azure Machine Learning",
        "Azure AI Foundry"
      ],
      "delivery": "预测模型与维护建议"
    },
    {
      "capability": "维护流程与现场联动",
      "products": [
        "Dynamics 365 Field Service",
        "Power Automate"
      ],
      "delivery": "维护任务和服务流程闭环"
    }
  ],
  
  "business_value": {
    "outcomes": [
      "提前识别高风险设备并减少被动报修",
      "提升维修准备效率和维护优先级判断质量",
      "降低重复故障和售后人工压力"
    ],
    "kpis": [
      "高风险设备提前识别率达到 75%",
      "非计划性报修下降 20%",
      "维护准备效率提升 30%"
    ],
    "deliverables": [
      "预测性维护场景图",
      "运营台原型建议",
      "POC 验证口径"
    ]
  },
  "poc": {
    "scope": "先验证设备健康评分、风险预测和维护动作联动三段闭环",
    "validation_points": [
      "高风险识别的业务可解释性",
      "预测建议对维修准备的帮助程度",
      "维护动作与工单闭环的可执行性"
    ],
    "stakeholders": [
      "售后运营负责人",
      "维修主管",
      "设备运营 / 数据团队"
    ],
    "next_actions": [
      "确认试点设备型号和样本维修记录",
      "选择一个高频故障场景作为试点",
      "两周内形成维护运营台原型和验证指标"
    ]
  }
}